deolingo/__init__.py
deolingo/__main__.py
deolingo/_answer_set_rewriter.py
deolingo/_application.py
deolingo/_ast_rewriting_transformer.py
deolingo/_ast_transformer.py
deolingo/_benchmark.py
deolingo/_deolingo_theory.py
deolingo/_deontic_atom.py
deolingo/_deontic_rules.py
deolingo/_generator.py
deolingo/_rewriting_translator.py
deolingo/_telingo_app.py
deolingo/_translator.py
deolingo/_version.py
deolingo/control.py
deolingo/deolingo_theory.lp
deolingo/deontic_rules.lp
deolingo/examples.py
deolingo/rewriting_control.py
deolingo/solver.py
deolingo/xcontrol.py
deolingo/xsolver.py
deolingo/domain/__init__.py
deolingo/domain/explain_deontic_program_command.py
deolingo/domain/generate_deontic_program_command.py
deolingo/domain/run_benchmark_command.py
deolingo/domain/solve_deontic_program_command.py
deolingo/domain/solve_temporal_deontic_program_command.py
deolingo/domain/use_case_command.py
deolingo/examples/benchmark/example1.lp
deolingo/examples/benchmark/example2.lp
deolingo/examples/benchmark/example3.lp
deolingo/examples/benchmark/example4.lp
deolingo/examples/benchmark/example5.lp
deolingo/examples/benchmark/example6.lp
deolingo/examples/benchmark/example7.lp
deolingo/examples/benchmark/example8.lp
deolingo/examples/delx/example1.1.lp
deolingo/examples/delx/example1.2.lp
deolingo/examples/delx/example2.lp
deolingo/examples/delx/example3.lp
deolingo/examples/delx/example4.lp
deolingo/examples/delx/example5.1.lp
deolingo/examples/delx/example5.2.lp
deolingo/examples/delx/example6.1.lp
deolingo/examples/delx/example6.2.alt.lp
deolingo/examples/delx/example6.2.lp
deolingo/examples/delxx/example1.1.lp
deolingo/examples/delxx/example1.2.lp
deolingo/examples/delxx/example2.lp
deolingo/examples/delxx/example3.lp
deolingo/examples/delxx/example4.lp
deolingo/examples/delxx/example5.1.lp
deolingo/examples/delxx/example5.2.lp
deolingo/examples/delxx/example6.1.lp
deolingo/examples/delxx/example6.2.lp
deolingo/examples/other/detachment.lp
deolingo/examples/other/traffic120.lp
deolingo-1.0.3.dist-info/licenses/LICENSE
deolingo-1.0.3.dist-info/METADATA
deolingo-1.0.3.dist-info/WHEEL
deolingo-1.0.3.dist-info/entry_points.txt
deolingo-1.0.3.dist-info/top_level.txt
deolingo-1.0.3.dist-info/RECORD
