Metadata-Version: 2.4
Name: deolingo
Version: 1.0.3
Summary: A deontic logic solver for explainable deontic reasoning with Answer Set Programming (ASP).
Home-page: https://github.com/ovidiomanteiga/deolingo
Author: Ovidio M. Moar
Author-email: ovidio.manteiga@udc.es
License: MIT
Keywords: ASP,NMR,Deontic Logic,SDL,Deontic Reasoning,Clingo,Xclingo,Telingo
Classifier: Development Status :: 3 - Alpha
Classifier: Intended Audience :: Developers
Classifier: Intended Audience :: Education
Classifier: Intended Audience :: Information Technology
Classifier: Intended Audience :: Legal Industry
Classifier: Intended Audience :: Science/Research
Classifier: License :: OSI Approved :: MIT License
Classifier: Operating System :: OS Independent
Classifier: Programming Language :: Python :: 3
Classifier: Programming Language :: Python :: 3.6
Classifier: Programming Language :: Python :: 3.7
Classifier: Programming Language :: Python :: 3.8
Classifier: Programming Language :: Python :: 3.9
Classifier: Programming Language :: Python :: 3.10
Classifier: Programming Language :: Python :: 3.11
Classifier: Programming Language :: Python :: 3.12
Classifier: Programming Language :: Python :: 3.13
Classifier: Programming Language :: Python :: 3.14
Classifier: Topic :: Software Development :: Interpreters
Classifier: Topic :: Software Development :: Libraries :: Python Modules
Classifier: Topic :: Utilities
License-File: LICENSE
Requires-Dist: cffi>=1.16.0
Requires-Dist: clingo>=5.7.1
Requires-Dist: clingox>=1.2.1
Requires-Dist: pycparser>=2.21
Requires-Dist: prettytable>=2.2.0
Requires-Dist: xclingo~=2.0b12
Requires-Dist: langchain~=0.1.0
Requires-Dist: openai~=1.30.1
Requires-Dist: langchain-openai~=0.1.7
Requires-Dist: gpt4all~=2.6.0
Requires-Dist: transformers~=4.40.2
Requires-Dist: google-generativeai~=0.5.3
Requires-Dist: telingo~=2.1.2
Requires-Dist: python-dotenv~=1.0.1
Dynamic: author
Dynamic: author-email
Dynamic: classifier
Dynamic: description
Dynamic: description-content-type
Dynamic: home-page
Dynamic: keywords
Dynamic: license
Dynamic: license-file
Dynamic: requires-dist
Dynamic: summary
